fave/FAAValign.py
fave/__init__.py
fave/align/README.md
fave/align/__init__.py
fave/align/aligner.py
fave/align/examples/align.mlf
fave/align/examples/code.scp
fave/align/examples/test/BREY00538.TextGrid
fave/align/examples/test/BREY00538.TextGrid.bk
fave/align/examples/test/BREY00538.txt
fave/align/examples/test/BREY00538.wav
fave/align/examples/test.scp
fave/align/examples/testref.mlf
fave/align/model/.com.apple.timemachine.supported
fave/align/model/11025/config
fave/align/model/11025/hmmdefs
fave/align/model/11025/macros
fave/align/model/16000/config
fave/align/model/16000/hmmdefs
fave/align/model/16000/macros
fave/align/model/16000 (old model)/config
fave/align/model/16000 (old model)/hmmdefs
fave/align/model/16000 (old model)/macros
fave/align/model/8000/config
fave/align/model/8000/hmmdefs
fave/align/model/8000/macros
fave/align/model/backups dicts/dict05172012
fave/align/model/backups dicts/dict_05232011
fave/align/model/backups dicts/dict_06222010
fave/align/model/backups dicts/dict_08222011
fave/align/model/backups dicts/dict_10192010
fave/align/model/backups dicts/dict_11022011
fave/align/model/backups dicts/dict_11092011
fave/align/model/backups dicts/dict_BACKUP
fave/align/model/backups dicts/dict_CELESTE_05232011
fave/align/model/backups dicts/dict_from_alignment_computer_11022011
fave/align/model/backups dicts/merged_dict_11022011
fave/align/model/dict
fave/align/model/g-dropping Jiahong/16000/hmmdefs
fave/align/model/g-dropping Jiahong/16000/macros
fave/align/model/g-dropping Jiahong/dict_G_DROPPING
fave/align/model/g-dropping Jiahong/dict_NEW_MERGED
fave/align/model/merge_dicts.py
fave/align/model/monophones
fave/align/old_docs/How to do forced aligment using FAAValign.pdf
fave/align/old_docs/How to install FAAValign.pdf
fave/align/readme_img/HTKLib-3.png
fave/align/readme_img/developer_downloads1.png
fave/align/readme_img/developer_downloads2.png
fave/align/readme_img/developer_downloads3.png
fave/align/readme_img/developer_login.png
fave-2.0.2.dist-info/entry_points.txt
fave-2.0.2.dist-info/LICENSE
fave-2.0.2.dist-info/WHEEL
fave-2.0.2.dist-info/METADATA
fave-2.0.2.dist-info/RECORD
