Metadata-Version: 2.1
Name: fave
Version: 2.0.2
Summary: Forced alignment and vowel extraction
Home-page: https://github.com/JoFrhwld/FAVE
License: GPL-3.0-only
Author: FAVE contributors
Requires-Python: >=3.8,<4.0
Classifier: License :: OSI Approved :: GNU General Public License v3 (GPLv3)
Classifier: Programming Language :: Python :: 3
Classifier: Programming Language :: Python :: 3.10
Classifier: Programming Language :: Python :: 3.8
Classifier: Programming Language :: Python :: 3.9
Requires-Dist: numpy (>=1.22,<2.0)
Requires-Dist: tqdm (>=4.64.0,<5.0.0)
